hypebankapi/__init__.py
hypebankapi/__main__.py
hypebankapi/banking.py
hypebankapi/hype.py
hypebankapi/utils.py
hypebankapi-1.1.0.dist-info/METADATA
hypebankapi-1.1.0.dist-info/WHEEL
hypebankapi-1.1.0.dist-info/licenses/LICENSE
hypebankapi-1.1.0.dist-info/RECORD
