Metadata-Version: 2.1
Name: HypeBankAPI
Version: 1.1.0
Summary: API for Hype card holders
Project-URL: Homepage, https://github.com/MatteoFasulo/HypeAPI/tree/pypi
Project-URL: Bug Tracker, https://github.com/MatteoFasulo/HypeAPI/issues
Author-email: Matteo Fasulo <mat.fasulo@gmail.com>
License-File: LICENSE
Classifier: License :: OSI Approved :: Apache Software License
Classifier: Natural Language :: English
Classifier: Operating System :: OS Independent
Classifier: Programming Language :: Python :: 3
Classifier: Programming Language :: Python :: 3.8
Requires-Python: >=3.7
Requires-Dist: lxml
Requires-Dist: requests
